{"changelogs_index.md":"BfrPtsJt","de_changelogs_index.md":"BNwHVN41","de_effects_effects.md":"BSLaVucS","de_effects_functions.md":"nBEAtJU4","de_effects_ourfirsteffect.md":"BRvyapR3","de_effects_ui.md":"D0yAPEXz","de_index.md":"ZrQvDt3j","de_user_advanced_advanced.md":"DSp-ZwuU","de_user_advanced_cli.md":"CWGqMuX-","de_user_advanced_support.md":"DRc5MFSj","de_user_advanced_testing.md":"BPhgS6-S","de_user_configuration.md":"DvEmWpMP","de_user_gettingstarted.md":"P05_u-Pa","de_user_hyperbian.md":"DX7p3VTg","de_user_introduction.md":"A1_UVjiY","de_user_leddevices_network_atmoorb.md":"TGq2DP8W","de_user_leddevices_network_cololight.md":"Dkdg7lb-","de_user_leddevices_network_fadecandy.md":"Bf-D5FDJ","de_user_leddevices_network_homeassistant.md":"A5zq3d03","de_user_leddevices_network_nanoleaf.md":"C8LB5pia","de_user_leddevices_network_philipshue.md":"C71x-VUy","de_user_leddevices_network_razer.md":"Bc_COGeg","de_user_leddevices_network_tinkerforge.md":"CyPG9j3D","de_user_leddevices_network_tpm2net.md":"CzYLBJSw","de_user_leddevices_network_udpartnet.md":"DQjjyR9Z","de_user_leddevices_network_udpddp.md":"CC71zIuO","de_user_leddevices_network_udpe131.md":"DvsulO-k","de_user_leddevices_network_udph801.md":"DfqhTULo","de_user_leddevices_network_udpraw.md":"DtsmIihH","de_user_leddevices_network_wled.md":"rmLTlqzF","de_user_leddevices_network_yeelight.md":"Czq3KVxv","de_user_leddevices_others_debug.md":"C711q1yd","de_user_leddevices_overview.md":"C5DDx_ws","de_user_leddevices_spi_pwm_apa102.md":"C9shHPkk","de_user_leddevices_spi_pwm_apa104.md":"Cn_VAM0o","de_user_leddevices_spi_pwm_hd108.md":"BYuO9IiL","de_user_leddevices_spi_pwm_lpd6803.md":"BK0j_IIy","de_user_leddevices_spi_pwm_lpd8806.md":"CxEQA1JG","de_user_leddevices_spi_pwm_p9813.md":"Eu03mDJQ","de_user_leddevices_spi_pwm_piblaster.md":"DOLIQfix","de_user_leddevices_spi_pwm_sk6812.md":"z5l_kJ4q","de_user_leddevices_spi_pwm_sk6822.md":"BLVqlfBI","de_user_leddevices_spi_pwm_sk9822.md":"BwVo6M94","de_user_leddevices_spi_pwm_ws2801.md":"SJAtlN3-","de_user_leddevices_spi_pwm_ws2812b.md":"BF02yc2Z","de_user_leddevices_usb_adalight.md":"BaokUQ8j","de_user_leddevices_usb_atmo.md":"DCr7FBS3","de_user_leddevices_usb_dmx.md":"DInASSl6","de_user_leddevices_usb_hyperion-usbasp.md":"Ds14vW0S","de_user_leddevices_usb_karate.md":"Cu3_SmkZ","de_user_leddevices_usb_lightpack.md":"BrMWfFx0","de_user_leddevices_usb_multilightpack.md":"jLyoNT7_","de_user_leddevices_usb_paintpack.md":"1xTjuhk8","de_user_leddevices_usb_rawhid.md":"Ng4nqjzl","de_user_leddevices_usb_sedu.md":"CvxnTBtF","de_user_leddevices_usb_skydimo.md":"B_dlmnvR","de_user_leddevices_usb_tpm2.md":"DoAaBht7","effects_effects.md":"3QJKurxJ","effects_functions.md":"DrtuKSdM","effects_ourfirsteffect.md":"DEKvd5AQ","effects_ui.md":"sVLlrwwb","index.md":"-Ouu3FYl","user_advanced_advanced.md":"BWy-Z8T_","user_advanced_cli.md":"DB71-zce","user_advanced_support.md":"DOmZkS9I","user_advanced_testing.md":"hZGxV4Md","user_configuration.md":"BzTGvC0S","user_gettingstarted.md":"Dyihp7cc","user_hyperbian.md":"BQmERGUD","user_introduction.md":"CtH6WHog","user_leddevices_network_atmoorb.md":"DIZJsuGJ","user_leddevices_network_cololight.md":"CYd-60L1","user_leddevices_network_fadecandy.md":"CTNe3mIs","user_leddevices_network_homeassistant.md":"DWN6y_qn","user_leddevices_network_nanoleaf.md":"BjlaVmuL","user_leddevices_network_philipshue.md":"Dh554Ga2","user_leddevices_network_razer.md":"B5Ff7Go4","user_leddevices_network_tinkerforge.md":"DfFLmn7a","user_leddevices_network_tpm2net.md":"B8eb7Fdd","user_leddevices_network_udpartnet.md":"DDhfXAlE","user_leddevices_network_udpddp.md":"SzorOs2r","user_leddevices_network_udpe131.md":"D1l8MTqb","user_leddevices_network_udph801.md":"DgayGFfT","user_leddevices_network_udpraw.md":"CIQGjjlt","user_leddevices_network_wled.md":"JXf4ntat","user_leddevices_network_yeelight.md":"BF57jrEC","user_leddevices_others_debug.md":"CktQciZL","user_leddevices_overview.md":"zPJXFMIl","user_leddevices_spi_pwm_apa102.md":"CN392PJD","user_leddevices_spi_pwm_apa104.md":"L6RVayNe","user_leddevices_spi_pwm_hd108.md":"PnI_nALR","user_leddevices_spi_pwm_lpd6803.md":"DwM7IrlW","user_leddevices_spi_pwm_lpd8806.md":"CIiYHkrD","user_leddevices_spi_pwm_p9813.md":"CbocaV6p","user_leddevices_spi_pwm_piblaster.md":"Byaux6bf","user_leddevices_spi_pwm_sk6812.md":"CO3cQG-c","user_leddevices_spi_pwm_sk6822.md":"D3gZgC0C","user_leddevices_spi_pwm_sk9822.md":"B-CoUtds","user_leddevices_spi_pwm_ws2801.md":"CYaaTq9J","user_leddevices_spi_pwm_ws2812b.md":"tCVKHEVS","user_leddevices_usb_adalight.md":"CQpUw5wS","user_leddevices_usb_atmo.md":"lkkA3QZ_","user_leddevices_usb_dmx.md":"C0kVtBxU","user_leddevices_usb_hyperion-usbasp.md":"BkuCAiG5","user_leddevices_usb_karate.md":"DyAtMrvB","user_leddevices_usb_lightpack.md":"DtX2ESI9","user_leddevices_usb_multilightpack.md":"DcL0lqrv","user_leddevices_usb_paintpack.md":"CmPFRe34","user_leddevices_usb_rawhid.md":"BAxKKAfC","user_leddevices_usb_sedu.md":"ByyQpwBO","user_leddevices_usb_skydimo.md":"ta3hx4Zh","user_leddevices_usb_tpm2.md":"Yes718-G"}
